mcp_clickhouse/__init__.py
mcp_clickhouse/main.py
mcp_clickhouse/mcp_env.py
mcp_clickhouse/mcp_server.py
mseep_mcp_clickhouse-0.1.9.dist-info/METADATA
mseep_mcp_clickhouse-0.1.9.dist-info/WHEEL
mseep_mcp_clickhouse-0.1.9.dist-info/entry_points.txt
mseep_mcp_clickhouse-0.1.9.dist-info/licenses/LICENSE
mseep_mcp_clickhouse-0.1.9.dist-info/RECORD
